django_dbreqresp/__init__.py
django_dbreqresp/admin.py
django_dbreqresp/apps.py
django_dbreqresp/decorator.py
django_dbreqresp/middleware.py
django_dbreqresp/models.py
django_dbreqresp/migrations/0001_initial.py
django_dbreqresp/migrations/__init__.py
django_dbreqresp-0.1.1.dist-info/licenses/LICENSE
django_dbreqresp-0.1.1.dist-info/METADATA
django_dbreqresp-0.1.1.dist-info/WHEEL
django_dbreqresp-0.1.1.dist-info/top_level.txt
django_dbreqresp-0.1.1.dist-info/RECORD
