Metadata-Version: 2.4
Name: django-dbreqresp
Version: 0.1.1
Author-email: Hashbang <contact@hashbang.coop>
License: This License grants rights to study, execute, modify and redistribute the
License-File: LICENSE
Requires-Dist: django
Provides-Extra: dev
Requires-Dist: ruff; extra == "dev"
Dynamic: license-file
